pyquadkey2/__init__.py
pyquadkey2/tilesystem.cpython-311-x86_64-linux-gnu.so
pyquadkey2/quadkey/__init__.py
pyquadkey2/quadkey/util.py
pyquadkey2-0.3.1.dist-info/LICENSE
pyquadkey2-0.3.1.dist-info/METADATA
pyquadkey2-0.3.1.dist-info/WHEEL
pyquadkey2-0.3.1.dist-info/top_level.txt
pyquadkey2-0.3.1.dist-info/RECORD
