Metadata-Version: 2.1
Name: pyquadkey2
Version: 0.3.1
Summary: Python implementation of geographical tiling using QuadKeys as proposed by Microsoft
Home-page: https://github.com/muety/pyquadkey2
Author: Ferdinand Mütsch
Author-email: ferdinand@muetsch.io
Project-URL: Bug Tracker, https://github.com/muety/pyquadkey2/issues
Project-URL: Source Code, https://github.com/muety/pyquadkey2
Project-URL: Documentation, https://docs.muetsch.io/pyquadkey2/
Keywords: tiling quadkey quadtile geospatial geohash
Classifier: Development Status :: 4 - Beta
Classifier: Programming Language :: Python :: 3
Classifier: Programming Language :: Cython
Classifier: License :: OSI Approved :: Apache Software License
Classifier: Operating System :: MacOS
Classifier: Operating System :: Unix
Classifier: Operating System :: POSIX :: Linux
Classifier: Natural Language :: English
Classifier: Topic :: Scientific/Engineering :: GIS
Classifier: Typing :: Typed
Requires-Python: >=3.10
License-File: LICENSE
